seqpool/__init__.py
seqpool/cvt.py
seqpool/mean.py
seqpool/utils.py
seqpool-0.0.1.dist-info/LICENSE
seqpool-0.0.1.dist-info/METADATA
seqpool-0.0.1.dist-info/WHEEL
seqpool-0.0.1.dist-info/top_level.txt
seqpool-0.0.1.dist-info/RECORD
