Metadata-Version: 2.1
Name: seqpool
Version: 0.0.1
Summary: SeqPool: Collection of pooling methods for sequences of embedding vectors
Home-page: https://github.com/vvvm23/seqpool
Author: Alex McKinney
Author-email: alexander.f.mckinney@durham.ac.uk
License: MIT License
Keywords: artificial intelligence,deep learning,pytorch
Classifier: Programming Language :: Python :: 3
Classifier: License :: OSI Approved :: MIT License
Classifier: Operating System :: OS Independent
Requires-Python: >=3.7
License-File: LICENSE
Requires-Dist: torch
